pyonedesk/__init__.py
pyonedesk/config.py
pyonedesk/main.py
pyonedesk/utils.py
pyonedesk/cli/__init__.py
pyonedesk/cli/commands.py
pyonedesk/server/__init__.py
pyonedesk/server/account.py
pyonedesk/server/admin.py
pyonedesk/server/index.py
pyonedesk/server/loop_task.py
pyonedesk/server/main.py
pyonedesk/server/onedrive.py
pyonedesk/server/utils.py
pyonedesk/server/win_thread.py
pyonedesk/server/res/admin.html
pyonedesk/server/res/admin_get_code.html
pyonedesk/server/res/admin_login.html
pyonedesk/server/res/favicon.ico
pyonedesk/server/res/index.html
pyonedesk/server/res/resources/css/admin.54962d20.css
pyonedesk/server/res/resources/css/admin_login.8cf9fc10.css
pyonedesk/server/res/resources/css/chunk-vendors.bc84d62c.css
pyonedesk/server/res/resources/css/index.4f523c1c.css
pyonedesk/server/res/resources/fonts/element-icons.535877f5.woff
pyonedesk/server/res/resources/fonts/element-icons.732389de.ttf
pyonedesk/server/res/resources/js/admin.f1f65107.js
pyonedesk/server/res/resources/js/admin_login.66fddfeb.js
pyonedesk/server/res/resources/js/chunk-vendors.b7630b4b.js
pyonedesk/server/res/resources/js/index.67affafb.js
pyonedesk-0.0.30.dist-info/METADATA
pyonedesk-0.0.30.dist-info/WHEEL
pyonedesk-0.0.30.dist-info/entry_points.txt
pyonedesk-0.0.30.dist-info/top_level.txt
pyonedesk-0.0.30.dist-info/zip-safe
pyonedesk-0.0.30.dist-info/RECORD
