Metadata-Version: 2.1
Name: pyonedesk
Version: 0.0.30
Summary: PyOneDesk
Home-page: https://github.com/gzlock/pyonedesk
Author: gzlock
Author-email: gzlock88@gmail.com
License: MIT
Keywords: OneDrive Web Desk
Platform: UNKNOWN
Classifier: Intended Audience :: Developers
Classifier: License :: OSI Approved :: MIT License
Classifier: Natural Language :: Chinese (Simplified)
Classifier: Programming Language :: Python :: 3.7
Classifier: Operating System :: MacOS :: MacOS X
Classifier: Operating System :: POSIX
Classifier: Operating System :: POSIX :: BSD
Classifier: Operating System :: POSIX :: Linux
Classifier: Operating System :: Microsoft :: Windows
Requires-Python: >=3.7
Requires-Dist: hurry.filesize
Requires-Dist: click
Requires-Dist: requests
Requires-Dist: sanic
Requires-Dist: diskcache
Requires-Dist: shortuuid
Requires-Dist: appdirs
